arithmetic/__init__.py
arithmetic/functions.py
mathme-0.1.0.dist-info/METADATA
mathme-0.1.0.dist-info/WHEEL
mathme-0.1.0.dist-info/top_level.txt
mathme-0.1.0.dist-info/RECORD
