Metadata-Version: 2.1
Name: mathme
Version: 0.1.0
Summary: My first Python library
Author: KHM
License: MIT
